asyncode.py
asyncode-1.0.0.dist-info/LICENSE
asyncode-1.0.0.dist-info/METADATA
asyncode-1.0.0.dist-info/WHEEL
asyncode-1.0.0.dist-info/top_level.txt
asyncode-1.0.0.dist-info/RECORD
