Metadata-Version: 2.1
Name: asyncode
Version: 1.0.0
Summary: Emulating Python's interactive interpreter in asynchronous contexts
Home-page: https://github.com/loic-simon/asyncode
Author: Loïc Simon
Author-email: loic.simon@espci.org
License: UNKNOWN
Platform: UNKNOWN
Classifier: Development Status :: 5 - Production/Stable
Classifier: Framework :: AsyncIO
Classifier: Intended Audience :: Developers
Classifier: Programming Language :: Python :: 3.5
Classifier: Programming Language :: Python :: 3.6
Classifier: Programming Language :: Python :: 3.7
Classifier: Programming Language :: Python :: 3.8
Classifier: Programming Language :: Python :: 3.9
Classifier: License :: OSI Approved :: MIT License
Classifier: Operating System :: OS Independent
Classifier: Topic :: Software Development :: Interpreters
Requires-Python: >=3.5
